upass/__init__.py
upass/__main__.py
upass/data/upass.ini.skel
upass-0.3.0.dist-info/METADATA
upass-0.3.0.dist-info/RECORD
upass-0.3.0.dist-info/WHEEL
upass-0.3.0.dist-info/entry_points.txt
upass-0.3.0.dist-info/top_level.txt
